README.md
setup.py
specsavers/__init__.py
specsavers/api.py
specsavers/appointment.py
specsavers/store.py
specsavers.egg-info/PKG-INFO
specsavers.egg-info/SOURCES.txt
specsavers.egg-info/dependency_links.txt
specsavers.egg-info/requires.txt
specsavers.egg-info/top_level.txt