Metadata-Version: 1.2
Name: specsavers
Version: 1.0
Summary: A Python wrapper around the Specsavers appointment booking API
Home-page: https://github.com/alxwrd/specsavers
Author: Alex Ward
Author-email: alxwrd@googlemail.com
License: MIT
Platform: UNKNOWN
Requires-Python: >=3.6
